flask_mysqlpooled.py
Flask_MySQLPooled-0.1.1.dist-info/METADATA
Flask_MySQLPooled-0.1.1.dist-info/WHEEL
Flask_MySQLPooled-0.1.1.dist-info/top_level.txt
Flask_MySQLPooled-0.1.1.dist-info/RECORD
