Metadata-Version: 2.1
Name: Flask-MySQLPooled
Version: 0.1.1
Summary: A Flask mysql pool extension based on DBUtils
Home-page: https://github.com/wanganhong/flask-mysqlpooled/
Author: wanganhong
Author-email: 773624972@qq.com
License: BSD
Platform: any
Classifier: Environment :: Web Environment
Classifier: Intended Audience :: Developers
Classifier: License :: OSI Approved :: BSD License
Classifier: Operating System :: OS Independent
Classifier: Programming Language :: Python
Classifier: Topic :: Internet :: WWW/HTTP :: Dynamic Content
Classifier: Topic :: Software Development :: Libraries :: Python Modules
Requires-Dist: Flask
Requires-Dist: PyMySQL
Requires-Dist: DBUtils
